cxflow_tensorflow/__init__.py
cxflow_tensorflow/frozen_model.py
cxflow_tensorflow/graph_tower.py
cxflow_tensorflow/model.py
cxflow_tensorflow/hooks/__init__.py
cxflow_tensorflow/hooks/decay_lr.py
cxflow_tensorflow/hooks/init_lr.py
cxflow_tensorflow/hooks/write_tensorboard.py
cxflow_tensorflow/metrics/__init__.py
cxflow_tensorflow/metrics/bin.py
cxflow_tensorflow/models/__init__.py
cxflow_tensorflow/models/blocks.py
cxflow_tensorflow/models/conv.py
cxflow_tensorflow/models/conv_blocks.py
cxflow_tensorflow/models/rnn.py
cxflow_tensorflow/models/rnn_blocks.py
cxflow_tensorflow/ops/__init__.py
cxflow_tensorflow/ops/flatten3d.py
cxflow_tensorflow/ops/loss.py
cxflow_tensorflow/ops/repeat.py
cxflow_tensorflow/ops/sparse.py
cxflow_tensorflow/third_party/__init__.py
cxflow_tensorflow/third_party/tensorflow/__init__.py
cxflow_tensorflow/third_party/tensorflow/average_gradients.py
cxflow_tensorflow/third_party/tensorflow/freeze_graph.py
cxflow_tensorflow/utils/__init__.py
cxflow_tensorflow/utils/reflection.py
cxflow_tensorflow-0.5.0.dist-info/METADATA
cxflow_tensorflow-0.5.0.dist-info/RECORD
cxflow_tensorflow-0.5.0.dist-info/WHEEL
cxflow_tensorflow-0.5.0.dist-info/top_level.txt
