Metadata-Version: 2.1
Name: cxflow-tensorflow
Version: 0.5.0
Summary: TensorFlow extension for cxflow.
Home-page: https://github.com/Cognexa/cxflow-tensorflow
Author: Cognexa Solutions s.r.o.
Author-email: info@cognexa.com
License: MIT
Keywords: tensorflow wrapper
Platform: UNKNOWN
Classifier: Development Status :: 4 - Beta
Classifier: Environment :: Console
Classifier: Intended Audience :: Developers
Classifier: Intended Audience :: Education
Classifier: Intended Audience :: Science/Research
Classifier: Operating System :: Unix
Classifier: Programming Language :: Python :: Implementation :: CPython
Classifier: Topic :: Scientific/Engineering :: Artificial Intelligence
Classifier: License :: OSI Approved :: MIT License
Classifier: Programming Language :: Python :: 3.5
Classifier: Programming Language :: Python :: 3.6
Requires-Dist: cxflow (>=0.8.1)
Requires-Dist: numpy (>=1.13.1)
